README
setup.py
wsgijson.py
wsgijson.egg-info/PKG-INFO
wsgijson.egg-info/SOURCES.txt
wsgijson.egg-info/dependency_links.txt
wsgijson.egg-info/requires.txt
wsgijson.egg-info/top_level.txt
wsgijson.egg-info/zip-safe