Metadata-Version: 1.0
Name: wsgijson
Version: 0.1
Summary: helpers for JSON-based WSGI services
Home-page: http://github.com/fivehut/wsgijson
Author: Casey Marks
Author-email: casey@fivehut.com
License: MIT
Keywords: wsgi,json
Platform: UNKNOWN
Classifier: Development Status :: 3 - Alpha
Classifier: License :: OSI Approved :: MIT License
